wukong/__init__.py
wukong/__main__.py
wukong/yuque.cfg
wukong/cli/__init__.py
wukong/cli/cli_parser.py
wukong/cli/commands/__init__.py
wukong/cli/commands/yuque.py
wukong/db/__init__.py
wukong/db/_impala.py
wukong/decorators/__init__.py
wukong/decorators/_progressbar.py
wukong/decorators/_retry.py
wukong/decorators/_timeit.py
wukong/robots/__init__.py
wukong/robots/_webcom.py
wukong/utils/__init__.py
wukong/utils/helpers.py
wukong/utils/model_loading.py
wu5kong-0.0.8.dist-info/LICENSE
wu5kong-0.0.8.dist-info/METADATA
wu5kong-0.0.8.dist-info/WHEEL
wu5kong-0.0.8.dist-info/entry_points.txt
wu5kong-0.0.8.dist-info/top_level.txt
wu5kong-0.0.8.dist-info/RECORD
