Metadata-Version: 2.1
Name: wu5kong
Version: 0.0.8
Summary: wu-kong package
Home-page: UNKNOWN
Author: yumingmin
Author-email: yu_mingm623@163.com
License: GPL
Platform: all
Classifier: Development Status :: 5 - Production/Stable
Classifier: Environment :: Console
Classifier: Environment :: Web Environment
Classifier: Intended Audience :: Developers
Classifier: Intended Audience :: System Administrators
Classifier: License :: OSI Approved :: Apache Software License
Classifier: Programming Language :: Python :: 3.8
Classifier: Programming Language :: Python :: 3.9
Classifier: Topic :: System :: Monitoring
Requires-Dist: rich (>=12.0.0)
Requires-Dist: rich[jupyter]
Requires-Dist: click (==8.0.4)
Requires-Dist: requests (>=2.25.1)
Requires-Dist: impyla (>=0.17.0)
Requires-Dist: pandas (>=1.3.1)
Requires-Dist: argcomplete (==2.0.0)
Requires-Dist: pyppeteer (==1.0.2)
Requires-Dist: pyppeteer-stealth (==2.7.3)
